facho/__init__.py
facho/cli.py
facho/facho.py
facho/fe/__init__.py
facho/fe/fe.py
facho/fe/client/__init__.py
facho/fe/client/dian.py
facho/fe/client/wsse/__init__.py
facho/fe/client/wsse/signature.py
facho/fe/data/__init__.py
facho/fe/data/dian/__init__.py
facho/fe/data/dian/politicadefirmav2.pdf
facho/fe/data/dian/XSD/__init__.py
facho/fe/data/dian/XSD/common/CCTS_CCT_SchemaModule-2.1.xsd
facho/fe/data/dian/XSD/common/UBL-CommonAggregateComponents-2.1.xsd
facho/fe/data/dian/XSD/common/UBL-CommonBasicComponents-2.1.xsd
facho/fe/data/dian/XSD/common/UBL-CommonExtensionComponents-2.1.xsd
facho/fe/data/dian/XSD/common/UBL-CommonSignatureComponents-2.1.xsd
facho/fe/data/dian/XSD/common/UBL-CoreComponentParameters-2.1.xsd
facho/fe/data/dian/XSD/common/UBL-ExtensionContentDataType-2.1.xsd
facho/fe/data/dian/XSD/common/UBL-QualifiedDataTypes-2.1.xsd
facho/fe/data/dian/XSD/common/UBL-SignatureAggregateComponents-2.1.xsd
facho/fe/data/dian/XSD/common/UBL-SignatureBasicComponents-2.1.xsd
facho/fe/data/dian/XSD/common/UBL-UnqualifiedDataTypes-2.1.xsd
facho/fe/data/dian/XSD/common/UBL-XAdESv132-2.1.xsd
facho/fe/data/dian/XSD/common/UBL-XAdESv141-2.1.xsd
facho/fe/data/dian/XSD/common/UBL-xmldsig-core-schema-2.1.xsd
facho/fe/data/dian/XSD/common/__init__.py
facho/fe/data/dian/XSD/maindoc/DIAN_UBL_Structures.xsd
facho/fe/data/dian/XSD/maindoc/UBL-ApplicationResponse-2.1.xsd
facho/fe/data/dian/XSD/maindoc/UBL-AttachedDocument-2.1.xsd
facho/fe/data/dian/XSD/maindoc/UBL-CreditNote-2.1.xsd
facho/fe/data/dian/XSD/maindoc/UBL-DebitNote-2.1.xsd
facho/fe/data/dian/XSD/maindoc/UBL-Invoice-2.1.xsd
facho/fe/data/dian/XSD/maindoc/__init__.py
facho/fe/data/dian/codelist/AlgoritmoCUDE-2.1.gc
facho/fe/data/dian/codelist/AlgoritmoCUFE-2.1.gc
facho/fe/data/dian/codelist/CodigoDescuento-2.1.gc
facho/fe/data/dian/codelist/CodigoPostal1.gc
facho/fe/data/dian/codelist/CodigoPrecioReferencia-2.1.gc
facho/fe/data/dian/codelist/ConceptoNotaCredito-2.1.gc
facho-0.2.1.dist-info/AUTHORS.rst
facho-0.2.1.dist-info/LICENSE
facho-0.2.1.dist-info/METADATA
facho-0.2.1.dist-info/WHEEL
facho-0.2.1.dist-info/entry_points.txt
facho-0.2.1.dist-info/top_level.txt
facho-0.2.1.dist-info/RECORD
