Metadata-Version: 2.1
Name: facho
Version: 0.2.1
Summary: Facturacion Electronica Colombia
Home-page: https://github.com/bit4bit/facho
Author: Jovany Leandro G.C
Author-email: bit4bit@riseup.net
License: GNU General Public License v3
Keywords: facho
Platform: UNKNOWN
Classifier: Development Status :: 2 - Pre-Alpha
Classifier: Intended Audience :: Developers
Classifier: License :: OSI Approved :: GNU General Public License v3 (GPLv3)
Classifier: Natural Language :: English
Classifier: Programming Language :: Python :: 3
Classifier: Programming Language :: Python :: 3.4
Classifier: Programming Language :: Python :: 3.5
Classifier: Programming Language :: Python :: 3.6
Classifier: Programming Language :: Python :: 3.7
License-File: LICENSE
License-File: AUTHORS.rst
Requires-Dist: Click (>=6.0)
Requires-Dist: zeep (>=3.4.0)
Requires-Dist: pyOpenSSL (>=19.1.0)
Requires-Dist: xmlsig (>=0.1.3)
Requires-Dist: xades (>=0.2.1)
Requires-Dist: mock (==2.0.0)
Requires-Dist: xmlsec (>=1.3.8)
